[
    {
        "usuario": "hi",
        "bot": " Hi! How are you? I just got back from walking my dog. Do you have any pets?"
    },
    {
        "usuario": "no, i dont have",
        "bot": " I'm sorry to hear that. Do you have any hobbies that you like to do?"
    },
    {
        "usuario": "",
        "bot": " Do you have any pets? I have a dog and he's my best friend."
    },
    {
        "usuario": "",
        "bot": " Do you have any pets? I have a dog and he's my best friend."
    }
]